pyunicodedata/__init__.py
pyunicodedata/pyunicodedata.py
pyunicodedata/14.0.0/ucd/ArabicShaping.txt
pyunicodedata/14.0.0/ucd/BidiBrackets.txt
pyunicodedata/14.0.0/ucd/BidiCharacterTest.txt
pyunicodedata/14.0.0/ucd/BidiMirroring.txt
pyunicodedata/14.0.0/ucd/BidiTest.txt
pyunicodedata/14.0.0/ucd/Blocks.txt
pyunicodedata/14.0.0/ucd/CJKRadicals.txt
pyunicodedata/14.0.0/ucd/CaseFolding.txt
pyunicodedata/14.0.0/ucd/CompositionExclusions.txt
pyunicodedata/14.0.0/ucd/DerivedAge.txt
pyunicodedata/14.0.0/ucd/DerivedCoreProperties.txt
pyunicodedata/14.0.0/ucd/DerivedNormalizationProps.txt
pyunicodedata/14.0.0/ucd/EastAsianWidth.txt
pyunicodedata/14.0.0/ucd/EmojiSources.txt
pyunicodedata/14.0.0/ucd/EquivalentUnifiedIdeograph.txt
pyunicodedata/14.0.0/ucd/HangulSyllableType.txt
pyunicodedata/14.0.0/ucd/Index.txt
pyunicodedata/14.0.0/ucd/IndicPositionalCategory.txt
pyunicodedata/14.0.0/ucd/IndicSyllabicCategory.txt
pyunicodedata/14.0.0/ucd/Jamo.txt
pyunicodedata/14.0.0/ucd/LineBreak.txt
pyunicodedata/14.0.0/ucd/NameAliases.txt
pyunicodedata/14.0.0/ucd/NamedSequences.txt
pyunicodedata/14.0.0/ucd/NamedSequencesProv.txt
pyunicodedata/14.0.0/ucd/NamesList.html
pyunicodedata/14.0.0/ucd/NamesList.txt
pyunicodedata/14.0.0/ucd/NormalizationCorrections.txt
pyunicodedata/14.0.0/ucd/NormalizationTest.txt
pyunicodedata/14.0.0/ucd/NushuSources.txt
pyunicodedata/14.0.0/ucd/PropList.txt
pyunicodedata/14.0.0/ucd/PropertyAliases.txt
pyunicodedata/14.0.0/ucd/PropertyValueAliases.txt
pyunicodedata/14.0.0/ucd/ReadMe.txt
pyunicodedata/14.0.0/ucd/ScriptExtensions.txt
pyunicodedata/14.0.0/ucd/Scripts.txt
pyunicodedata/14.0.0/ucd/SpecialCasing.txt
pyunicodedata/14.0.0/ucd/StandardizedVariants.txt
pyunicodedata/14.0.0/ucd/TangutSources.txt
pyunicodedata/14.0.0/ucd/USourceData.txt
pyunicodedata/14.0.0/ucd/USourceGlyphs.pdf
pyunicodedata/14.0.0/ucd/USourceRSChart.pdf
pyunicodedata/14.0.0/ucd/UnicodeData.txt
pyunicodedata/14.0.0/ucd/Unihan_DictionaryIndices.txt
pyunicodedata-0.0.6.dist-info/METADATA
pyunicodedata-0.0.6.dist-info/WHEEL
pyunicodedata-0.0.6.dist-info/top_level.txt
pyunicodedata-0.0.6.dist-info/RECORD
